.gitignore
MANIFEST.in
README.rst
setup.py
S3D.egg-info/PKG-INFO
S3D.egg-info/SOURCES.txt
S3D.egg-info/dependency_links.txt
S3D.egg-info/entry_points.txt
S3D.egg-info/requires.txt
S3D.egg-info/top_level.txt
s3deploy/__init__.py
s3deploy/script.py