Metadata-Version: 1.0
Name: S3D
Version: 1.0.0
Summary: s3deploy
Home-page: https://github.com/tayhobbs/s3deploy
Author: Taylor Hobbs
Author-email: hobbstay@gmail.com.com
License: UNKNOWN
Platform: UNKNOWN
